dev.py
intel.py
america-0.0.1.dist-info/METADATA
america-0.0.1.dist-info/WHEEL
america-0.0.1.dist-info/top_level.txt
america-0.0.1.dist-info/RECORD
