Metadata-Version: 2.1
Name: america
Version: 0.0.1
Summary: so sus
Author: ja cob
Classifier: Programming Language :: Python :: 3
Classifier: License :: OSI Approved :: MIT License
Classifier: Operating System :: OS Independent
Requires-Python: >=3.6
